.gitignore
COPYING
LICENSE
README.md
setup.py
icoshift/__init__.py
icoshift/icoshift.py
icoshift/tests.py
icoshift.egg-info/PKG-INFO
icoshift.egg-info/SOURCES.txt
icoshift.egg-info/dependency_links.txt
icoshift.egg-info/requires.txt
icoshift.egg-info/top_level.txt