Metadata-Version: 1.1
Name: icoshift
Version: 0.7
Summary: icoshift: A versatile tool for the rapid alignment of 1D NMR spectra
Home-page: https://github.com/mfitzp/icoshift
Author: Martin Fitzpatrick
Author-email: martin.fitzpatrick@gmail.com
License: GPL
Download-URL: https://github.com/mfitzp/icoshift/zipball/master
Keywords: bioinformatics metabolomics research analysis science
Platform: UNKNOWN
Classifier: Development Status :: 4 - Beta
Classifier: Natural Language :: English
Classifier: Operating System :: OS Independent
Classifier: Programming Language :: Python :: 2
Classifier: License :: OSI Approved :: BSD License
Classifier: Topic :: Scientific/Engineering :: Bio-Informatics
Classifier: Intended Audience :: Science/Research
Classifier: Intended Audience :: Education
